rename_lock/__init__.py
rename_lock/test.py
rename_lock-0.1.4.dist-info/METADATA
rename_lock-0.1.4.dist-info/WHEEL
rename_lock-0.1.4.dist-info/top_level.txt
rename_lock-0.1.4.dist-info/RECORD
