Metadata-Version: 2.1
Name: rename-lock
Version: 0.1.4
Summary: Easy file exclusive locking tool based on file rename
Home-page: https://github.co.jp/
Author: bib_inf
Author-email: contact.bibinf@gmail.com
License: CC0 v1.0
Platform: UNKNOWN
Classifier: Programming Language :: Python :: 3
Classifier: License :: CC0 1.0 Universal (CC0 1.0) Public Domain Dedication
Requires-Dist: ezpip
Requires-Dist: sout
Requires-Dist: fies
